{"general_figure_info": {"figure_info": {"bbox": {"x": 95, "y": 108, "w": 646.0999755859375, "h": 385.5}}, "title": {"bbox": {"x": 14, "y": 12, "w": 689.859375, "h": 29.015625}, "text": "Annual CO\u2082 emissions from deforestation for food production"}, "x_axis": {"major_labels": {"bboxes": [{"x": 10, "y": 151, "w": 80.765625, "h": 15.015625}, {"x": 54, "y": 279, "w": 36.765625, "h": 15.015625}, {"x": 35, "y": 408, "w": 56.03125, "h": 15.015625}], "values": ["South Korea", "Spain", "Slovenia"]}}, "y_axis": {"major_labels": {"bboxes": [{"x": 86, "y": 500, "w": 18.53125, "h": 18}, {"x": 213, "y": 500, "w": 68.9375, "h": 18}, {"x": 360, "y": 500, "w": 77.9375, "h": 18}, {"x": 511, "y": 500, "w": 77.953125, "h": 18}, {"x": 663, "y": 500, "w": 77.953125, "h": 18}], "values": ["0 t", "5 million t", "10 million t", "15 million t", "20 million t"]}}}, "models": [{"name": "bars", "bboxes": [{"x": 95, "y": 108, "w": 646.0999755859375, "h": 102.80001068115234}, {"x": 95, "y": 236, "w": 597.4000244140625, "h": 102.79998779296875}, {"x": 95, "y": 365, "w": 29.599998474121094, "h": 102.79998779296875}], "y": ["21.32 million t", "19.72 million t", "977,633 t"], "x": ["South Korea", "Spain", "Slovenia"], "colors": ["#00847e", "#b13507", "#3c4e66"]}], "type": "h_bar"}