{"general_figure_info": {"figure_info": {"bbox": {"x": 134, "y": 35, "w": 576, "h": 461}}, "y_axis": {"label": {"bbox": [{"x": 356, "y": 527, "w": 132.296875, "h": 11}], "text": "Number of paid vacation days"}, "major_labels": {"bboxes": [{"x": 113.5, "y": 502, "w": 44.0, "h": 26.0}, {"x": 185.5, "y": 502, "w": 44.0, "h": 26.0}, {"x": 257.5, "y": 502, "w": 44.0, "h": 26.0}, {"x": 329.5, "y": 502, "w": 44.0, "h": 26.0}, {"x": 401.5, "y": 502, "w": 44.0, "h": 26.0}, {"x": 473.5, "y": 502, "w": 44.0, "h": 26.0}, {"x": 545.5, "y": 502, "w": 44.0, "h": 26.0}, {"x": 617.5, "y": 502, "w": 44.0, "h": 26.0}, {"x": 690.5, "y": 502, "w": 44.0, "h": 26.0}]}}, "x_axis": {"major_labels": {"bboxes": [{"x": 55, "y": 50, "h": 12, "w": 66.53759765625}, {"x": 91, "y": 92, "h": 12, "w": 29.984375}, {"x": 78, "y": 134, "h": 12, "w": 43.67919921875}, {"x": 93, "y": 176, "h": 12, "w": 27.515625}, {"x": 43, "y": 218, "h": 12, "w": 78.28125}, {"x": 93, "y": 260, "h": 12, "w": 28.140625}, {"x": 76, "y": 301, "h": 12, "w": 45.7353515625}, {"x": 101, "y": 343, "h": 12, "w": 20.673828125}, {"x": 87, "y": 385, "h": 12, "w": 34.50537109375}, {"x": 87, "y": 427, "h": 12, "w": 34.25}, {"x": 50, "y": 469, "h": 12, "w": 71.34375}], "values": ["United States", "Japan", "Australia", "Brazil", "United Kingdom", "Spain", "Germany", "Italy", "Russia", "France", "World average"]}, "label": {}}, "legend": {"bbox": {"x": 153, "y": 556, "w": 438, "h": 34}, "items": [{"model": "Allotted paid vacation days", "label": {"bbox": {"x": 419, "y": 568, "w": 155.693359375, "h": 14}, "text": "Allotted paid vacation days"}, "preview": {"bbox": {"x": 400, "y": 568, "w": 12, "h": 12}}}, {"model": "Paid vacation days considered fair", "label": {"bbox": {"x": 182, "y": 568, "w": 197.73828125, "h": 14}, "text": "Paid vacation days considered fair"}, "preview": {"bbox": {"x": 163, "y": 568, "w": 12, "h": 12}}}]}}, "models": [{"name": "Allotted paid vacation days", "bboxes": [{"x": 133, "y": 39, "w": 259, "h": 16}, {"x": 133, "y": 81, "w": 274, "h": 16}, {"x": 133, "y": 123, "w": 317, "h": 16}, {"x": 133, "y": 165, "w": 346, "h": 16}, {"x": 133, "y": 207, "w": 346, "h": 16}, {"x": 133, "y": 249, "w": 346, "h": 16}, {"x": 133, "y": 291, "w": 374, "h": 16}, {"x": 133, "y": 332, "w": 389, "h": 16}, {"x": 133, "y": 374, "w": 418, "h": 16}, {"x": 133, "y": 416, "w": 446, "h": 16}, {"x": 133, "y": 458, "w": 346, "h": 16}], "colors": ["#0f283e", "#0f283e", "#0f283e", "#0f283e", "#0f283e", "#0f283e", "#0f283e", "#0f283e", "#0f283e", "#0f283e", "#0f283e"], "y": ["18", "19", "22", "24", "24", "24", "26", "27", "29", "31", "24"], "labels": ["United States", "Japan", "Australia", "Brazil", "United Kingdom", "Spain", "Germany", "Italy", "Russia", "France", "World average"], "x": ["United States", "Japan", "Australia", "Brazil", "United Kingdom", "Spain", "Germany", "Italy", "Russia", "France", "World average"]}, {"name": "Paid vacation days considered fair", "bboxes": [{"x": 133, "y": 56, "w": 317, "h": 16}, {"x": 133, "y": 98, "w": 403, "h": 16}, {"x": 133, "y": 140, "w": 346, "h": 16}, {"x": 133, "y": 182, "w": 475, "h": 16}, {"x": 133, "y": 224, "w": 403, "h": 16}, {"x": 133, "y": 266, "w": 461, "h": 16}, {"x": 133, "y": 308, "w": 432, "h": 16}, {"x": 133, "y": 350, "w": 446, "h": 16}, {"x": 133, "y": 392, "w": 475, "h": 16}, {"x": 133, "y": 434, "w": 446, "h": 16}, {"x": 133, "y": 476, "w": 418, "h": 16}], "colors": ["#2876dd", "#2876dd", "#2876dd", "#2876dd", "#2876dd", "#2876dd", "#2876dd", "#2876dd", "#2876dd", "#2876dd", "#2876dd"], "y": ["22", "28", "24", "33", "28", "32", "30", "31", "33", "31", "29"], "labels": ["United States", "Japan", "Australia", "Brazil", "United Kingdom", "Spain", "Germany", "Italy", "Russia", "France", "World average"], "x": ["United States", "Japan", "Australia", "Brazil", "United Kingdom", "Spain", "Germany", "Italy", "Russia", "France", "World average"]}], "type": "h_bar"}